cognee_community_vector_adapter_qdrant/QdrantDatasetDatabaseHandler.py
cognee_community_vector_adapter_qdrant/__init__.py
cognee_community_vector_adapter_qdrant/qdrant_adapter.py
cognee_community_vector_adapter_qdrant/register.py
cognee_community_vector_adapter_qdrant-0.2.0.dist-info/METADATA
cognee_community_vector_adapter_qdrant-0.2.0.dist-info/WHEEL
cognee_community_vector_adapter_qdrant-0.2.0.dist-info/RECORD
