Metadata-Version: 2.4
Name: cognee-community-vector-adapter-qdrant
Version: 0.2.0
Summary: Qdrant vector database adapter for cognee
Requires-Python: >=3.11,<=3.13
Classifier: Programming Language :: Python :: 3
Classifier: Programming Language :: Python :: 3.11
Classifier: Programming Language :: Python :: 3.12
Classifier: Programming Language :: Python :: 3.13
Requires-Dist: cognee (==0.5.1)
Requires-Dist: instructor (>=1.11)
Requires-Dist: qdrant-client (>=1.16.0)
Requires-Dist: starlette (>=0.48.0)
